ipaddress.py
ipaddress-1.0.21.dist-info/LICENSE.txt
ipaddress-1.0.21.dist-info/METADATA
ipaddress-1.0.21.dist-info/RECORD
ipaddress-1.0.21.dist-info/WHEEL
ipaddress-1.0.21.dist-info/top_level.txt
